Workbook

Sheet CC 2023
E2: Employee Name | L2: =CONCATENATE(G146,"/",Q174) -> #DIV/0!
E3: 2023
E4: Part 1: Ice Breaker : Introduction & General Feedback
E6: Role:
E7: Reports to:
E8: Start Date:
E10: Mid-year meeting
E11: End-of-year meeting
E14: How do you feel? Any ideas for BWD to improve ? | G14: ='CC 2023'!E2 -> Employee Name | L14: out of 10
E15: =CONCATENATE("Mid-year meeting - ", TEXT($F$10,"dd/mm/yyyy")) -> Mid-year meeting - 00/01/1900 | F15: What is going well in my role
F16: What is challenging in my role
F17: How is BWD as an Employer ( management style, culture, work environment)
F18: Average | G18: =AVERAGE(L15:L17) -> #DIV/0!
E19: =CONCATENATE("End-of-year meeting - ", TEXT($F$11,"dd/mm/yyyy")) -> End-of-year meeting - 00/01/1900 | F19: What is going well
F20: What is challenging
F21: How is BWD as an Employer ( management style, culture, work environment)
F22: Average | G22: =AVERAGE(L19:L21) -> #DIV/0!
E25: Part 2: Your skill set & Learning Plan
E26: Just checking your current skill-set and exploring new competences to develop.
E28: SKILL 1
E29: =CONCATENATE("Mid-year meeting - ", TEXT($F$10,"dd/mm/yyyy")) -> Mid-year meeting - 00/01/1900 | G29: ='CC 2023'!E2 -> Employee Name | J29: =F7 -> 0
E31: =CONCATENATE("End-of-year meeting - ", TEXT($F$11,"dd/mm/yyyy")) -> End-of-year meeting - 00/01/1900 | G31: ='CC 2023'!E2 -> Employee Name | J31: =F7 -> 0
E34: SKILL 2
E35: =CONCATENATE("Mid-year meeting - ", TEXT($F$10,"dd/mm/yyyy")) -> Mid-year meeting - 00/01/1900 | G35: ='CC 2023'!E2 -> Employee Name | J35: =F7 -> 0
E37: =CONCATENATE("End-of-year meeting - ", TEXT($F$11,"dd/mm/yyyy")) -> End-of-year meeting - 00/01/1900 | G37: ='CC 2023'!E2 -> Employee Name | J37: =F7 -> 0
E40: SKILL 3
E41: =CONCATENATE("Mid-year meeting - ", TEXT($F$10,"dd/mm/yyyy")) -> Mid-year meeting - 00/01/1900 | G41: ='CC 2023'!E2 -> Employee Name | J41: =F7 -> 0
E43: =CONCATENATE("End-of-year meeting - ", TEXT($F$11,"dd/mm/yyyy")) -> End-of-year meeting - 00/01/1900 | G43: ='CC 2023'!E2 -> Employee Name | J43: =F7 -> 0
E46: SKILL 4
E47: =CONCATENATE("Mid-year meeting - ", TEXT($F$10,"dd/mm/yyyy")) -> Mid-year meeting - 00/01/1900 | G47: ='CC 2023'!E2 -> Employee Name | J47: =F7 -> 0
E49: =CONCATENATE("End-of-year meeting - ", TEXT($F$11,"dd/mm/yyyy")) -> End-of-year meeting - 00/01/1900 | G49: ='CC 2023'!E2 -> Employee Name | J49: =F7 -> 0
E52: SKILL 5
E53: =CONCATENATE("Mid-year meeting - ", TEXT($F$10,"dd/mm/yyyy")) -> Mid-year meeting - 00/01/1900 | G53: ='CC 2023'!E2 -> Employee Name | J53: =F7 -> 0
E55: =CONCATENATE("End-of-year meeting - ", TEXT($F$11,"dd/mm/yyyy")) -> End-of-year meeting - 00/01/1900 | G55: ='CC 2023'!E2 -> Employee Name | J55: =F7 -> 0
E58: SKILL 6
E59: =CONCATENATE("Mid-year meeting - ", TEXT($F$10,"dd/mm/yyyy")) -> Mid-year meeting - 00/01/1900 | G59: ='CC 2023'!E2 -> Employee Name | J59: =F7 -> 0
E61: =CONCATENATE("End-of-year meeting - ", TEXT($F$11,"dd/mm/yyyy")) -> End-of-year meeting - 00/01/1900 | G61: ='CC 2023'!E2 -> Employee Name | J61: =F7 -> 0
E64: SKILL 7
E65: =CONCATENATE("Mid-year meeting - ", TEXT($F$10,"dd/mm/yyyy")) -> Mid-year meeting - 00/01/1900 | G65: ='CC 2023'!E2 -> Employee Name | J65: =F7 -> 0
E67: =CONCATENATE("End-of-year meeting - ", TEXT($F$11,"dd/mm/yyyy")) -> End-of-year meeting - 00/01/1900 | G67: ='CC 2023'!E2 -> Employee Name | J67: =F7 -> 0
E71: Based on your skill-set and growth plan, what is your learning target? Plan, Track, Celebrate!
E72: Training required (description, link) | G72: Format | H72: Timeline | I72: Budget | J72: Supported by BWD? | K72: % of accomplishment | L72: Training's review (/10)
E83: Part 3: SMART Goals
E84: With the help of your manager, and based on your current KPIs and ambition, define 5 SMART goals that you will accomplish for the next 12 months. The most significant will be included in your next year KPIs and used for your bonus calculation. No worries, if a goal is not applicable anymore, just do not fill a percentage and it will not be taken into account.
E85: Feeling lost? Check out this link -> | G85: Examples of SMART Goals
F86: GOAL1
E87: Short description | F87: Talent Acquisition ( 100% fast & successful recruitments ) 2023
E88: Make it SMART | F88: Specific | I88: Measurable | J88: Achievable | K88: Relevant | L88: Time-bound
F89: Ensure hiring managers satisfaction by providing quickly strong shortlists of candidates, smooth interviews process and guidance in the decision | I89: 100% hiring manager satisfaction 100% new employee success after 6 months | J89: thanks to a strong culture and employer branding, a good collaboration with managers and sharp recruitment tools & techniques | K89: to support BWD performance and growth | L89: by the end of 2023 | O89: =IF(L89="Fails to meet objective", 4, IF(L89="Partially meets objective", 3, IF(L89="Meets expectations", 2, IF(L89="Exceeds expectations", 1,IF(L89="To be done", ""))))) -> FALSE
F90: ='CC 2023'!E2 -> Employee Name
F91: % accomplished | H91: Comments
E92: =CONCATENATE("Mid-year meeting - ", TEXT($F$10,"dd/mm/yyyy")) -> Mid-year meeting - 00/01/1900
E93: =CONCATENATE("End-of-year meeting - ", TEXT($F$11,"dd/mm/yyyy")) -> End-of-year meeting - 00/01/1900
F94: =F7 -> 0
F95: % accomplished | H95: Comments
E96: =CONCATENATE("Mid-year meeting - ", TEXT($F$10,"dd/mm/yyyy")) -> Mid-year meeting - 00/01/1900
E97: =CONCATENATE("End-of-year meeting - ", TEXT($F$11,"dd/mm/yyyy")) -> End-of-year meeting - 00/01/1900
F98: GOAL 2
E99: Short description
E100: Make it SMART | F100: Specific | I100: Measurable | J100: Achievable | K100: Relevant | L100: Time-bound
O101: =IF(L101="Fails to meet objective", 4, IF(L101="Partially meets objective", 3, IF(L101="Meets expectations", 2, IF(L101="Exceeds expectations", 1,IF(L101="To be done", ""))))) -> FALSE
F102: ='CC 2023'!E2 -> Employee Name
F103: % accomplished | H103: Comments
E104: =CONCATENATE("Mid-year meeting - ", TEXT($F$10,"dd/mm/yyyy")) -> Mid-year meeting - 00/01/1900
E105: =CONCATENATE("End-of-year meeting - ", TEXT($F$11,"dd/mm/yyyy")) -> End-of-year meeting - 00/01/1900
F106: =F7 -> 0
F107: % accomplished | H107: Comments
E108: =CONCATENATE("Mid-year meeting - ", TEXT($F$10,"dd/mm/yyyy")) -> Mid-year meeting - 00/01/1900
E109: =CONCATENATE("End-of-year meeting - ", TEXT($F$11,"dd/mm/yyyy")) -> End-of-year meeting - 00/01/1900
F110: GOAL 3
E111: Short description
E112: Make it SMART | F112: Specific | I112: Measurable | J112: Achievable | K112: Relevant | L112: Time-bound
O113: =IF(L113="Fails to meet objective", 4, IF(L113="Partially meets objective", 3, IF(L113="Meets expectations", 2, IF(L113="Exceeds expectations", 1,IF(L113="To be done", ""))))) -> FALSE
F114: ='CC 2023'!E2 -> Employee Name
F115: % accomplished | H115: Comments
E116: =CONCATENATE("Mid-year meeting - ", TEXT($F$10,"dd/mm/yyyy")) -> Mid-year meeting - 00/01/1900
E117: =CONCATENATE("End-of-year meeting - ", TEXT($F$11,"dd/mm/yyyy")) -> End-of-year meeting - 00/01/1900
F118: =F7 -> 0
F119: % accomplished | H119: Comments
E120: =CONCATENATE("Mid-year meeting - ", TEXT($F$10,"dd/mm/yyyy")) -> Mid-year meeting - 00/01/1900
E121: =CONCATENATE("End-of-year meeting - ", TEXT($F$11,"dd/mm/yyyy")) -> End-of-year meeting - 00/01/1900
F122: GOAL 4
E123: Short description
E124: Make it SMART | F124: Specific | I124: Measurable | J124: Achievable | K124: Relevant | L124: Time-bound
O125: =IF(L125="Fails to meet objective", 4, IF(L125="Partially meets objective", 3, IF(L125="Meets expectations", 2, IF(L125="Exceeds expectations", 1,IF(L125="To be done", ""))))) -> FALSE
F126: ='CC 2023'!E2 -> Employee Name
F127: % accomplished | H127: Comments
E128: =CONCATENATE("Mid-year meeting - ", TEXT($F$10,"dd/mm/yyyy")) -> Mid-year meeting - 00/01/1900
E129: =CONCATENATE("End-of-year meeting - ", TEXT($F$11,"dd/mm/yyyy")) -> End-of-year meeting - 00/01/1900
F130: =F7 -> 0
F131: % accomplished | H131: Comments
E132: =CONCATENATE("Mid-year meeting - ", TEXT($F$10,"dd/mm/yyyy")) -> Mid-year meeting - 00/01/1900
E133: =CONCATENATE("End-of-year meeting - ", TEXT($F$11,"dd/mm/yyyy")) -> End-of-year meeting - 00/01/1900
F134: GOAL 5
E135: Short description
E136: Make it SMART | F136: Specific | I136: Measurable | J136: Achievable | K136: Relevant | L136: Time-bound
O137: =IF(L137="Fails to meet objective", 4, IF(L137="Partially meets objective", 3, IF(L137="Meets expectations", 2, IF(L137="Exceeds expectations", 1,IF(L137="To be done", ""))))) -> FALSE
F138: ='CC 2023'!E2 -> Employee Name
F139: % accomplished | H139: Comments
E140: =CONCATENATE("Mid-year meeting - ", TEXT($F$10,"dd/mm/yyyy")) -> Mid-year meeting - 00/01/1900
...

Sheet Ramp Up Model
D2: ='CC 2023'!E2 -> Employee Name | K2: =CONCATENATE($L$231,$K$193) -> #VALUE!
D4: Part 1 : Ice Breaker : Introduction & General Feedback
D5: New Role | E5: Full Stack Developer
D6: Reports to | E6: Anael
D7: Context | E7: Akshat Replacement - Akshat last day of work if 1/5/2024
D10: Job Description* | E10: As the Full Stack Developer, you will report to the Director - Engineering and IT and play a critical role in designing, developing, deploying, maintaining, and supporting our diverse range of applications. Your efforts will be closely aligned with our IT strategy and product roadmap, ensuring our technological solutions remain at the forefront of industry standards. Key tasks and responsibilities Participate in strategic decision-making and contribute to the design of the 2023 Roadmap Report to the manager on collaboration and projects, and proactively offer solutions Participate in designing and implementing the software architecture and applications Review, identify, propose, and implement changes in our current application stacks, in collaboration with IT system team, to optimize costs and reduce maintenance In accordance with company cybersecurity roadmap and industry best practices, adapt, improve and update internal applications to be compliant with written policies. ldentify, test, recommend, develop and deploy applications and tools including and not limited to Java related technologies and frameworks that are relevant to the business requirements of the company. ldentify, assess, advise on, develop and implement centralized software development tools and development guidelines and processes that are the state of the art in implementing front-end and back-end applications Maintain updated overview of the software stack and applications, their interactions and user documentations Participate in and facilitate code reviews with peers
E13: 2023 KPIs | J13: 1
E14: COMPANY PERFORMANCE | J14: 0.3
E15: 2023 Order Intake
E16: 2023 Cost Management
E17: 2023 Return on Capital Employed
E18: TEAM GOALS* | J18: 0.2
E23: SMART GOALS* | J23: 0.3
E28: COMPANY VALUES AMBASSADOR | J28: 0.2
E29: Quality
E30: Innovation
E31: Collaboration
E32: Customer centricity
E36: Start date | I36: 45329
E37: Meeting 1 (during 1st week) | I37: 15/02/2024
E38: Meeting 2 | I38: 45369
E39: Meeting 3 | I39: 15/04/2024
D41: Part 1: Introduction & General Feedback
D42: How do you feel? Any ideas for BWD to improve ? | F42: Team member | J42: Manager
D43: =CONCATENATE("Meeting 1 - ", TEXT(I37,"dd/mm/yyyy")) -> Meeting 1 - 15/02/2024 | E43: What is going well in my role | F43: Things are going well, have everything he needs, will request more services and accesses later on. | I43: 8 | J43: Akshat : confirms he will give access later. Good 1st week - Anael : MCP should be available. Good 1st success with a alarm problem solved. He has a lot to discover.
E44: What is challenging in my role | F44: get familiar to tools
E45: How is BWD as an Employer ( management style, culture, work environment) | F45: Nice people, good environment , quite relax, efficiency | I45: 9 | J45: Marie encourages to catchup with Thasa and Graham
E46: Average | F46: =AVERAGE(I43:I45) -> 8.5
D47: =CONCATENATE("Meeting 2 - ", TEXT(I38,"dd/mm/yyyy")) -> Meeting 2 - 18/03/2024 | E47: What is going well in my role | F47: Transfer is shared session by session, with practical opportunity in between | I47: 9 | J47: exceptional job since last month , Oscar is almost autonomous / confirmed bby Anael, ex Pat dashboard
E48: What is challenging in my role | F48: some apps are complex and require more time : NRMS > need more practice | J48: there will be more session and work on NRMS
E49: How is BWD as an Employer ( management style, culture, work environment) | F49: people are still nice and helpful | I49: 9
E50: Average | F50: =AVERAGE(I47:I49) -> 9
D51: =CONCATENATE("Meeting 3 - ", TEXT(I39,"dd/mm/yyyy")) -> Meeting 3 - 15/04/2024 | E51: What is going well in my role | I51: 0
E52: What is challenging in my role
E53: How is BWD as an Employer ( management style, culture, work environment)
E54: Average | F54: =AVERAGE(I51:I53) -> 0
D58: Part 2: Skills Audit and Upskilling Plan
D59: Let's check how comfortable you feel for each main component of your new role. Identify any gaps and create an upskilling plan to help you become an expert. This plan will involve formal training and learning by doing. Monitor the progression with your % of autonomy.
D61: SKILL 1* | F61: Technology – Spring Boot, Java , MySQL , Graph DB , Docker, Groovy, Node.js , Angular , SQL, Unix , shell scripts
D62: =CONCATENATE("Meeting 1 - ", TEXT($I$37,"dd/mm/yyyy")) -> Meeting 1 - 15/02/2024 | G62: Team member | I62: Manager*
F63: 0.7 | G63: familiar with all of them : 85% , expect Angular and MySQL : 55% | I63: agreed
D64: =CONCATENATE("Meeting 2 - ", TEXT($I$38,"dd/mm/yyyy")) -> Meeting 2 - 18/03/2024 | G64: Team member | I64: Manager
F65: 0.8 | G65: no change in Angular 55%, feel better in SQL and others | I65: Pentahu is still a challenge, but others are progressing well.
D66: =CONCATENATE("Meeting 3 - ", TEXT($I$39,"dd/mm/yyyy")) -> Meeting 3 - 15/04/2024 | G66: Team member | I66: Manager
F67: 0
D69: SKILL 2* | F69: Tools - Grafana, GitLab, Jenkins , Confluence , OTRS , JIRA, OpenNMS , MariaDb , Postgres DB
D70: =CONCATENATE("Meeting 1 - ", TEXT($I$37,"dd/mm/yyyy")) -> Meeting 1 - 15/02/2024 | G70: Team member | I70: Manager
F71: 0.9 | G71: familiar with al l of them, grafana, gitlab, jenkins : OK / expect OpenNms | I71: Akshat to train Oscar on OpenNMS
D72: =CONCATENATE("Meeting 2 - ", TEXT($I$38,"dd/mm/yyyy")) -> Meeting 2 - 18/03/2024 | G72: Team member | I72: Manager
F73: 0.95 | G73: all good for all of them, needs to practice on Jenkins set up BWD , openNMS | I73: agreed, demo to be organised
D74: =CONCATENATE("Meeting 3 - ", TEXT($I$39,"dd/mm/yyyy")) -> Meeting 3 - 15/04/2024 | G74: Team member | I74: Manager
F75: 0
D77: SKILL 3* | F77: Integration – Pentahu
D78: =CONCATENATE("Meeting 1 - ", TEXT($I$37,"dd/mm/yyyy")) -> Meeting 1 - 15/02/2024 | G78: Team member | I78: Manager
F79: 0.2 | G79: New framework , has used similar tools
D80: =CONCATENATE("Meeting 2 - ", TEXT($I$38,"dd/mm/yyyy")) -> Meeting 2 - 18/03/2024 | G80: Team member | I80: Manager
F81: 0.6 | G81: Pentahu has been used last | I81: agreed - Oscar is independent on Pentahu
D82: =CONCATENATE("Meeting 3 - ", TEXT($I$39,"dd/mm/yyyy")) -> Meeting 3 - 15/04/2024 | G82: Team member | I82: Manager
F83: 0
D85: SKILL 4*
D86: =CONCATENATE("Meeting 1 - ", TEXT($I$37,"dd/mm/yyyy")) -> Meeting 1 - 15/02/2024 | G86: Team member | I86: Manager
F87: 0
D88: =CONCATENATE("Meeting 2 - ", TEXT($I$38,"dd/mm/yyyy")) -> Meeting 2 - 18/03/2024 | G88: Team member | I88: Manager
F89: 0
D90: =CONCATENATE("Meeting 3 - ", TEXT($I$39,"dd/mm/yyyy")) -> Meeting 3 - 15/04/2024 | G90: Team member | I90: Manager
F91: 0
D93: SKILL 5*
D94: =CONCATENATE("Meeting 1 - ", TEXT($I$37,"dd/mm/yyyy")) -> Meeting 1 - 15/02/2024 | G94: Team member | I94: Manager
F95: 0
D96: =CONCATENATE("Meeting 2 - ", TEXT($I$38,"dd/mm/yyyy")) -> Meeting 2 - 18/03/2024 | G96: Team member | I96: Manager
F97: 0
D98: =CONCATENATE("Meeting 3 - ", TEXT($I$39,"dd/mm/yyyy")) -> Meeting 3 - 15/04/2024 | G98: Team member | I98: Manager
F99: 0
D101: SKILL 6*
D102: =CONCATENATE("Meeting 1 - ", TEXT($I$37,"dd/mm/yyyy")) -> Meeting 1 - 15/02/2024 | G102: Team member | I102: Manager
F103: 0
D104: =CONCATENATE("Meeting 2 - ", TEXT($I$38,"dd/mm/yyyy")) -> Meeting 2 - 18/03/2024 | G104: Team member | I104: Manager
F105: 0
D106: =CONCATENATE("Meeting 3 - ", TEXT($I$39,"dd/mm/yyyy")) -> Meeting 3 - 15/04/2024 | G106: Team member | I106: Manager
F107: 0
D109: SKILL 7*
D110: =CONCATENATE("Meeting 1 - ", TEXT($I$37,"dd/mm/yyyy")) -> Meeting 1 - 15/02/2024 | G110: Team member | I110: Manager
D112: =CONCATENATE("Meeting 2 - ", TEXT($I$38,"dd/mm/yyyy")) -> Meeting 2 - 18/03/2024 | G112: Team member | I112: Manager
F113: 0
D114: =CONCATENATE("Meeting 3 - ", TEXT($I$39,"dd/mm/yyyy")) -> Meeting 3 - 15/04/2024 | G114: Team member | I114: Manager
F115: 0
D119: Part 3: SMART Goals
D120: What can be achieved during your induction period ? Define your 5 priorities.Split your goals accordingly to ensure they are smart.
D121: Feeling lost? Check out this link -> | F121: Examples of SMART Goals
E122: GOAL1
D123: Short description | E123: Add new dashboards in Stats Portal (https://stats-new.local.bw-digital.com/)
D124: Make it SMART | E124: Specific | G124: Measurable | H124: Achievable | I124: Relevant | K124: Time-bound
E125: Eng. Team new feature requests | G125: Diagram of active fibers and historical table of 5 last switches | H125: With Akshat and Pat Support | I125: To implement new features / improve traffic visibility | K125: Q2 2024 | N125: =IF(K125="Fails to meet objective", 4, IF(K125="Partially meets objective", 3, IF(K125="Meets expectations", 2, IF(K125="Exceeds expectations", 1,IF(K125="To be done", ""))))) -> FALSE
E126: Team member
E127: % accomplished | F127: Comments
D128: =CONCATENATE("Meeting 1 - ", TEXT($I$37,"dd/mm/yyyy")) -> Meeting 1 - 15/02/2024
D129: =CONCATENATE("Meeting 2 - ", TEXT($I$38,"dd/mm/yyyy")) -> Meeting 2 - 18/03/2024 | E129: 0.8 | F129: out of 3 parts, part 1 and 3 completed, being reviewed by Pat , part2 Network diagram is not completed as Oscar needs support for Akshat - Discussion with Pat will help
D130: =CONCATENATE("Meeting 3 - ", TEXT($I$39,"dd/mm/yyyy")) -> Meeting 3 - 15/04/2024
E131: Manager
E132: % accomplished | F132: Comments
...

Sheet CC 2024
E2: ='CC 2023'!E2 -> Employee Name | L2: =CONCATENATE(G146,"/",Q174) -> #DIV/0!
E3: 2023
E4: Part 1: Ice Breaker : Introduction & General Feedback
E6: Role: | F6: Full Stack Developer
E7: Reports to: | F7: Anael
E8: Start Date: | F8: 45475
E10: Mid-year meeting
E11: End-of-year meeting
E14: How do you feel? Any ideas for BWD to improve ? | G14: ='CC 2023'!E2 -> Employee Name | L14: out of 10
E15: =CONCATENATE("Mid-year meeting - ", TEXT($F$10,"dd/mm/yyyy")) -> Mid-year meeting - 00/01/1900 | F15: What is going well in my role
F16: What is challenging in my role
F17: How is BWD as an Employer ( management style, culture, work environment)
F18: Average | G18: =AVERAGE(L15:L17) -> #DIV/0!
E19: =CONCATENATE("End-of-year meeting - ", TEXT($F$11,"dd/mm/yyyy")) -> End-of-year meeting - 00/01/1900 | F19: What is going well
F20: What is challenging
F21: How is BWD as an Employer ( management style, culture, work environment)
F22: Average | G22: =AVERAGE(L19:L21) -> #DIV/0!
E25: Part 2: Your skill set & Learning Plan
E26: Just checking your current skill-set and exploring new competences to develop.
E28: SKILL 1 | F28: Technology – Spring Boot, Java , MySQL , Graph DB , Docker, Groovy, Node.js , Angular , SQL, Unix , shell scripts
E29: =CONCATENATE("Mid-year meeting - ", TEXT($F$10,"dd/mm/yyyy")) -> Mid-year meeting - 00/01/1900 | G29: ='CC 2023'!E2 -> Employee Name | J29: =F7 -> Anael
E31: =CONCATENATE("End-of-year meeting - ", TEXT($F$11,"dd/mm/yyyy")) -> End-of-year meeting - 00/01/1900 | G31: ='CC 2023'!E2 -> Employee Name | J31: =F7 -> Anael
E34: SKILL 2 | F34: Tools - Grafana, GitLab, Jenkins , Confluence , OTRS , JIRA, OpenNMS , MariaDb , Postgres DB
E35: =CONCATENATE("Mid-year meeting - ", TEXT($F$10,"dd/mm/yyyy")) -> Mid-year meeting - 00/01/1900 | G35: ='CC 2023'!E2 -> Employee Name | J35: =F7 -> Anael
E37: =CONCATENATE("End-of-year meeting - ", TEXT($F$11,"dd/mm/yyyy")) -> End-of-year meeting - 00/01/1900 | G37: ='CC 2023'!E2 -> Employee Name | J37: =F7 -> Anael
E40: SKILL 3 | F40: Integration – Pentahu
E41: =CONCATENATE("Mid-year meeting - ", TEXT($F$10,"dd/mm/yyyy")) -> Mid-year meeting - 00/01/1900 | G41: ='CC 2023'!E2 -> Employee Name | J41: =F7 -> Anael
E43: =CONCATENATE("End-of-year meeting - ", TEXT($F$11,"dd/mm/yyyy")) -> End-of-year meeting - 00/01/1900 | G43: ='CC 2023'!E2 -> Employee Name | J43: =F7 -> Anael
E46: SKILL 4
E47: =CONCATENATE("Mid-year meeting - ", TEXT($F$10,"dd/mm/yyyy")) -> Mid-year meeting - 00/01/1900 | G47: ='CC 2023'!E2 -> Employee Name | J47: =F7 -> Anael
E49: =CONCATENATE("End-of-year meeting - ", TEXT($F$11,"dd/mm/yyyy")) -> End-of-year meeting - 00/01/1900 | G49: ='CC 2023'!E2 -> Employee Name | J49: =F7 -> Anael
E52: SKILL 5
E53: =CONCATENATE("Mid-year meeting - ", TEXT($F$10,"dd/mm/yyyy")) -> Mid-year meeting - 00/01/1900 | G53: ='CC 2023'!E2 -> Employee Name | J53: =F7 -> Anael
E55: =CONCATENATE("End-of-year meeting - ", TEXT($F$11,"dd/mm/yyyy")) -> End-of-year meeting - 00/01/1900 | G55: ='CC 2023'!E2 -> Employee Name | J55: =F7 -> Anael
E58: SKILL 6
E59: =CONCATENATE("Mid-year meeting - ", TEXT($F$10,"dd/mm/yyyy")) -> Mid-year meeting - 00/01/1900 | G59: ='CC 2023'!E2 -> Employee Name | J59: =F7 -> Anael
E61: =CONCATENATE("End-of-year meeting - ", TEXT($F$11,"dd/mm/yyyy")) -> End-of-year meeting - 00/01/1900 | G61: ='CC 2023'!E2 -> Employee Name | J61: =F7 -> Anael
E64: SKILL 7
E65: =CONCATENATE("Mid-year meeting - ", TEXT($F$10,"dd/mm/yyyy")) -> Mid-year meeting - 00/01/1900 | G65: ='CC 2023'!E2 -> Employee Name | J65: =F7 -> Anael
E67: =CONCATENATE("End-of-year meeting - ", TEXT($F$11,"dd/mm/yyyy")) -> End-of-year meeting - 00/01/1900 | G67: ='CC 2023'!E2 -> Employee Name | J67: =F7 -> Anael
E71: Based on your skill-set and growth plan, what is your learning target? Plan, Track, Celebrate!
E72: Training required (description, link) | G72: Format | H72: Timeline | I72: Budget | J72: Supported by BWD? | K72: % of accomplishment | L72: Training's review (/10)
E83: Part 3: SMART Goals
E84: With the help of your manager, and based on your current KPIs and ambition, define 5 SMART goals that you will accomplish for the next 12 months. The most significant will be included in your next year KPIs and used for your bonus calculation. No worries, if a goal is not applicable anymore, just do not fill a percentage and it will not be taken into account.
E85: Feeling lost? Check out this link -> | G85: Examples of SMART Goals
F86: GOAL1
E87: Short description | F87: Support container architecture
E88: Make it SMART | F88: Specific | I88: Measurable | J88: Achievable | K88: Relevant | L88: Time-bound
F89: Be proficient on troubleshooting the newly migrated servers onto containers. | I89: Be able to fix issues | J89: With Akshat knowledge transfer | K89: We need a ressource able to maintain this when Akshat has left. | L89: By 31/05/2024 | O89: =IF(L89="Fails to meet objective", 4, IF(L89="Partially meets objective", 3, IF(L89="Meets expectations", 2, IF(L89="Exceeds expectations", 1,IF(L89="To be done", ""))))) -> FALSE
F90: ='CC 2023'!E2 -> Employee Name
F91: % accomplished | H91: Comments
E92: =CONCATENATE("Mid-year meeting - ", TEXT($F$10,"dd/mm/yyyy")) -> Mid-year meeting - 00/01/1900
E93: =CONCATENATE("End-of-year meeting - ", TEXT($F$11,"dd/mm/yyyy")) -> End-of-year meeting - 00/01/1900
F94: =F7 -> Anael
F95: % accomplished | H95: Comments
E96: =CONCATENATE("Mid-year meeting - ", TEXT($F$10,"dd/mm/yyyy")) -> Mid-year meeting - 00/01/1900
E97: =CONCATENATE("End-of-year meeting - ", TEXT($F$11,"dd/mm/yyyy")) -> End-of-year meeting - 00/01/1900
F98: GOAL 2
E99: Short description | F99: Improve NRMS usability
E100: Make it SMART | F100: Specific | I100: Measurable | J100: Achievable | K100: Relevant | L100: Time-bound
F101: In collaboration with NOC and Thasa, evaluate, prioritize, and improve features/GUI to make NRMS more user friendly. | I101: Based on targets defined by Thasa/NOC | J101: With support of NOC & Thasa | K101: NRMS is our primary tool to manage ressources and it must be "sexy" to use. | L101: Q3 2024 | O101: =IF(L101="Fails to meet objective", 4, IF(L101="Partially meets objective", 3, IF(L101="Meets expectations", 2, IF(L101="Exceeds expectations", 1,IF(L101="To be done", ""))))) -> FALSE
F102: ='CC 2023'!E2 -> Employee Name
F103: % accomplished | H103: Comments
E104: =CONCATENATE("Mid-year meeting - ", TEXT($F$10,"dd/mm/yyyy")) -> Mid-year meeting - 00/01/1900
E105: =CONCATENATE("End-of-year meeting - ", TEXT($F$11,"dd/mm/yyyy")) -> End-of-year meeting - 00/01/1900
F106: =F7 -> Anael
F107: % accomplished | H107: Comments
E108: =CONCATENATE("Mid-year meeting - ", TEXT($F$10,"dd/mm/yyyy")) -> Mid-year meeting - 00/01/1900
E109: =CONCATENATE("End-of-year meeting - ", TEXT($F$11,"dd/mm/yyyy")) -> End-of-year meeting - 00/01/1900
F110: GOAL 3
E111: Short description | F111: Allow Service delivery team to provision new services on stats portal & NRMS
E112: Make it SMART | F112: Specific | I112: Measurable | J112: Achievable | K112: Relevant | L112: Time-bound
F113: Each time we onboard or remove a circuit/customer, IT-Dev is involved to manually create the entries in Stats portal, NRMS and Customer Portal. I'd like this process to be handled by Service Delivery team. | I113: 100% successfull usage by Service Delivery team | J113: by designing and implementing tool | K113: To reduce load on IT-DEV and allow SD to be autonomous | L113: Q4 2024 | O113: =IF(L113="Fails to meet objective", 4, IF(L113="Partially meets objective", 3, IF(L113="Meets expectations", 2, IF(L113="Exceeds expectations", 1,IF(L113="To be done", ""))))) -> FALSE
F114: ='CC 2023'!E2 -> Employee Name
F115: % accomplished | H115: Comments
E116: =CONCATENATE("Mid-year meeting - ", TEXT($F$10,"dd/mm/yyyy")) -> Mid-year meeting - 00/01/1900
E117: =CONCATENATE("End-of-year meeting - ", TEXT($F$11,"dd/mm/yyyy")) -> End-of-year meeting - 00/01/1900
F118: =F7 -> Anael
F119: % accomplished | H119: Comments
E120: =CONCATENATE("Mid-year meeting - ", TEXT($F$10,"dd/mm/yyyy")) -> Mid-year meeting - 00/01/1900
E121: =CONCATENATE("End-of-year meeting - ", TEXT($F$11,"dd/mm/yyyy")) -> End-of-year meeting - 00/01/1900
F122: GOAL 4
E123: Short description | F123: Investigate how a chatbot / AI can help NOC operations
E124: Make it SMART | F124: Specific | I124: Measurable | J124: Achievable | K124: Relevant | L124: Time-bound
F125: Based on the ticket information, NRMS data, Stats portal data, identify and suggest how AI/Chatbot can help daily operations of the NOC / Service Delivery | I125: prototype delivered to Anael / roadmap ready to be implemented in 2025 | J125: thanks to Exploration / gather Akshat researchs | K125: To facilitate NOC / Service delivery gathering of information | L125: Q4 2024 | O125: =IF(L125="Fails to meet objective", 4, IF(L125="Partially meets objective", 3, IF(L125="Meets expectations", 2, IF(L125="Exceeds expectations", 1,IF(L125="To be done", ""))))) -> FALSE
F126: ='CC 2023'!E2 -> Employee Name
F127: % accomplished | H127: Comments
E128: =CONCATENATE("Mid-year meeting - ", TEXT($F$10,"dd/mm/yyyy")) -> Mid-year meeting - 00/01/1900
E129: =CONCATENATE("End-of-year meeting - ", TEXT($F$11,"dd/mm/yyyy")) -> End-of-year meeting - 00/01/1900
F130: =F7 -> Anael
F131: % accomplished | H131: Comments
E132: =CONCATENATE("Mid-year meeting - ", TEXT($F$10,"dd/mm/yyyy")) -> Mid-year meeting - 00/01/1900
E133: =CONCATENATE("End-of-year meeting - ", TEXT($F$11,"dd/mm/yyyy")) -> End-of-year meeting - 00/01/1900
F134: GOAL 5
E135: Short description | F135: Deliver on User Requests
E136: Make it SMART | F136: Specific | I136: Measurable | J136: Achievable | K136: Relevant | L136: Time-bound
F137: To be able to support Eng, NOC, Service Delivery teams new feature requests and support existing systems | I137: 1-100 % New feature requests implemented 2- support - No major concern raised by relevant teams & most of the issues should get fixed within resonable timeframes | J137: Yes, after knowledge transfer | K137: To be able to maintain existing resources managed by Dev Team | L137: Q2 2024 | O137: =IF(L137="Fails to meet objective", 4, IF(L137="Partially meets objective", 3, IF(L137="Meets expectations", 2, IF(L137="Exceeds expectations", 1,IF(L137="To be done", ""))))) -> FALSE
F138: ='CC 2023'!E2 -> Employee Name
F139: % accomplished | H139: Comments
E140: =CONCATENATE("Mid-year meeting - ", TEXT($F$10,"dd/mm/yyyy")) -> Mid-year meeting - 00/01/1900
...

Sheet CC 2025
E2: ='CC 2023'!E2 -> Employee Name | L2: =CONCATENATE(G146,"/",Q174) -> #DIV/0!
E3: 2024
E4: Part 1: Ice Breaker : Introduction & General Feedback
E6: Role: | F6: ='CC 2024'!F6 -> Full Stack Developer
E7: Reports to: | F7: ='CC 2024'!F7 -> Anael
E8: Start Date: | F8: ='CC 2024'!F8 -> 45475
E10: Mid-year meeting | F10: TBD
E11: End-of-year meeting | F11: TBD
E14: How do you feel? Any ideas for BWD to improve ? | G14: ='CC 2023'!E2 -> Employee Name | L14: out of 10
E15: =CONCATENATE("Mid-year meeting - ", TEXT($F$10,"dd/mm/yyyy")) -> Mid-year meeting - TBD | F15: What is going well in my role
F16: What is challenging in my role
F17: How is BWD as an Employer ( management style, culture, work environment)
F18: Average | G18: =AVERAGE(L15:L17) -> #DIV/0!
E19: =CONCATENATE("End-of-year meeting - ", TEXT($F$11,"dd/mm/yyyy")) -> End-of-year meeting - TBD | F19: What is going well
F20: What is challenging
F21: How is BWD as an Employer ( management style, culture, work environment)
F22: Average | G22: =AVERAGE(L19:L21) -> #DIV/0!
E25: Part 2: Your skill set & Learning Plan
E26: Just checking your current skill-set and exploring new competences to develop.
E28: SKILL 1 | F28: ='CC 2024'!F28 -> Technology – Spring Boot, Java , MySQL , Graph DB , Docker, Groovy, Node.js , Angular , SQL, Unix , shell scripts
E29: =CONCATENATE("Mid-year meeting - ", TEXT($F$10,"dd/mm/yyyy")) -> Mid-year meeting - TBD | G29: ='CC 2023'!E2 -> Employee Name | J29: =F7 -> Anael
E31: =CONCATENATE("End-of-year meeting - ", TEXT($F$11,"dd/mm/yyyy")) -> End-of-year meeting - TBD | G31: ='CC 2023'!E2 -> Employee Name | J31: =F7 -> Anael
E34: SKILL 2 | F34: ='CC 2024'!F34 -> Tools - Grafana, GitLab, Jenkins , Confluence , OTRS , JIRA, OpenNMS , MariaDb , Postgres DB
E35: =CONCATENATE("Mid-year meeting - ", TEXT($F$10,"dd/mm/yyyy")) -> Mid-year meeting - TBD | G35: ='CC 2023'!E2 -> Employee Name | J35: =F7 -> Anael
E37: =CONCATENATE("End-of-year meeting - ", TEXT($F$11,"dd/mm/yyyy")) -> End-of-year meeting - TBD | G37: ='CC 2023'!E2 -> Employee Name | J37: =F7 -> Anael
E40: SKILL 3 | F40: ='CC 2024'!F40 -> Integration – Pentahu
E41: =CONCATENATE("Mid-year meeting - ", TEXT($F$10,"dd/mm/yyyy")) -> Mid-year meeting - TBD | G41: ='CC 2023'!E2 -> Employee Name | J41: =F7 -> Anael
E43: =CONCATENATE("End-of-year meeting - ", TEXT($F$11,"dd/mm/yyyy")) -> End-of-year meeting - TBD | G43: ='CC 2023'!E2 -> Employee Name | J43: =F7 -> Anael
E46: SKILL 4 | F46: ='CC 2024'!F46 -> 0
E47: =CONCATENATE("Mid-year meeting - ", TEXT($F$10,"dd/mm/yyyy")) -> Mid-year meeting - TBD | G47: ='CC 2023'!E2 -> Employee Name | J47: =F7 -> Anael
E49: =CONCATENATE("End-of-year meeting - ", TEXT($F$11,"dd/mm/yyyy")) -> End-of-year meeting - TBD | G49: ='CC 2023'!E2 -> Employee Name | J49: =F7 -> Anael
E52: SKILL 5 | F52: ='CC 2024'!F52 -> 0
E53: =CONCATENATE("Mid-year meeting - ", TEXT($F$10,"dd/mm/yyyy")) -> Mid-year meeting - TBD | G53: ='CC 2023'!E2 -> Employee Name | J53: =F7 -> Anael
E55: =CONCATENATE("End-of-year meeting - ", TEXT($F$11,"dd/mm/yyyy")) -> End-of-year meeting - TBD | G55: ='CC 2023'!E2 -> Employee Name | J55: =F7 -> Anael
E58: SKILL 6 | F58: ='CC 2024'!F58 -> 0
E59: =CONCATENATE("Mid-year meeting - ", TEXT($F$10,"dd/mm/yyyy")) -> Mid-year meeting - TBD | G59: ='CC 2023'!E2 -> Employee Name | J59: =F7 -> Anael
E61: =CONCATENATE("End-of-year meeting - ", TEXT($F$11,"dd/mm/yyyy")) -> End-of-year meeting - TBD | G61: ='CC 2023'!E2 -> Employee Name | J61: =F7 -> Anael
E64: SKILL 7 | F64: ='CC 2024'!F64 -> 0
E65: =CONCATENATE("Mid-year meeting - ", TEXT($F$10,"dd/mm/yyyy")) -> Mid-year meeting - TBD | G65: ='CC 2023'!E2 -> Employee Name | J65: =F7 -> Anael
E67: =CONCATENATE("End-of-year meeting - ", TEXT($F$11,"dd/mm/yyyy")) -> End-of-year meeting - TBD | G67: ='CC 2023'!E2 -> Employee Name | J67: =F7 -> Anael
E71: Based on your skill-set and growth plan, what is your learning target? Plan, Track, Celebrate!
E72: Training required (description, link) | G72: Format | H72: Timeline | I72: Budget | J72: Supported by BWD? | K72: % of accomplishment | L72: Training's review (/10)
E83: Part 3: SMART Goals
E84: With the help of your manager, and based on your current KPIs and ambition, define 5 SMART goals that you will accomplish for the next 12 months. The most significant will be included in your next year KPIs and used for your bonus calculation. No worries, if a goal is not applicable anymore, just do not fill a percentage and it will not be taken into account.
E85: Feeling lost? Check out this link -> | G85: Examples of SMART Goals
F86: GOAL1
E87: Short description | F87: ='CC 2024'!F87 -> Support container architecture
E88: Make it SMART | F88: Specific | I88: Measurable | J88: Achievable | K88: Relevant | L88: Time-bound
F89: ='CC 2024'!F89 -> Be proficient on troubleshooting the newly migrated servers onto containers. | I89: ='CC 2024'!I89 -> Be able to fix issues | J89: ='CC 2024'!J89 -> With Akshat knowledge transfer | K89: ='CC 2024'!K89 -> We need a ressource able to maintain this when Akshat has left. | L89: ='CC 2024'!L89 -> By 31/05/2024 | O89: =IF(L89="Fails to meet objective", 4, IF(L89="Partially meets objective", 3, IF(L89="Meets expectations", 2, IF(L89="Exceeds expectations", 1,IF(L89="To be done", ""))))) -> FALSE
F90: ='CC 2023'!E2 -> Employee Name
F91: % accomplished | H91: Comments
E92: =CONCATENATE("Mid-year meeting - ", TEXT($F$10,"dd/mm/yyyy")) -> Mid-year meeting - TBD
E93: =CONCATENATE("End-of-year meeting - ", TEXT($F$11,"dd/mm/yyyy")) -> End-of-year meeting - TBD
F94: =F7 -> Anael
F95: % accomplished | H95: Comments
E96: =CONCATENATE("Mid-year meeting - ", TEXT($F$10,"dd/mm/yyyy")) -> Mid-year meeting - TBD
E97: =CONCATENATE("End-of-year meeting - ", TEXT($F$11,"dd/mm/yyyy")) -> End-of-year meeting - TBD
F98: GOAL 2
E99: Short description | F99: ='CC 2024'!F99 -> Improve NRMS usability
E100: Make it SMART | F100: Specific | I100: Measurable | J100: Achievable | K100: Relevant | L100: Time-bound
F101: ='CC 2024'!F101 -> In collaboration with NOC and Thasa, evaluate, prioritize, and improve features/GUI to make NRMS more user friendly. | I101: ='CC 2024'!I101 -> Based on targets defined by Thasa/NOC | J101: ='CC 2024'!J101 -> With support of NOC & Thasa | K101: ='CC 2024'!K101 -> NRMS is our primary tool to manage ressources and it must be "sexy" to use. | L101: ='CC 2024'!L101 -> Q3 2024 | O101: =IF(L101="Fails to meet objective", 4, IF(L101="Partially meets objective", 3, IF(L101="Meets expectations", 2, IF(L101="Exceeds expectations", 1,IF(L101="To be done", ""))))) -> FALSE
F102: ='CC 2023'!E2 -> Employee Name
F103: % accomplished | H103: Comments
E104: =CONCATENATE("Mid-year meeting - ", TEXT($F$10,"dd/mm/yyyy")) -> Mid-year meeting - TBD
E105: =CONCATENATE("End-of-year meeting - ", TEXT($F$11,"dd/mm/yyyy")) -> End-of-year meeting - TBD
F106: =F7 -> Anael
F107: % accomplished | H107: Comments
E108: =CONCATENATE("Mid-year meeting - ", TEXT($F$10,"dd/mm/yyyy")) -> Mid-year meeting - TBD
E109: =CONCATENATE("End-of-year meeting - ", TEXT($F$11,"dd/mm/yyyy")) -> End-of-year meeting - TBD
F110: GOAL 3
E111: Short description | F111: ='CC 2024'!F111 -> Allow Service delivery team to provision new services on stats portal & NRMS
E112: Make it SMART | F112: Specific | I112: Measurable | J112: Achievable | K112: Relevant | L112: Time-bound
F113: ='CC 2024'!F113 -> Each time we onboard or remove a circuit/customer, IT-Dev is involved to manually create the entries in Stats portal, NRMS and Customer Portal. I'd like this process to be handled by Service Delivery team. | I113: ='CC 2024'!I113 -> 100% successfull usage by Service Delivery team | J113: ='CC 2024'!J113 -> by designing and implementing tool | K113: ='CC 2024'!K113 -> To reduce load on IT-DEV and allow SD to be autonomous | L113: ='CC 2024'!L113 -> Q4 2024 | O113: =IF(L113="Fails to meet objective", 4, IF(L113="Partially meets objective", 3, IF(L113="Meets expectations", 2, IF(L113="Exceeds expectations", 1,IF(L113="To be done", ""))))) -> FALSE
F114: ='CC 2023'!E2 -> Employee Name
F115: % accomplished | H115: Comments
E116: =CONCATENATE("Mid-year meeting - ", TEXT($F$10,"dd/mm/yyyy")) -> Mid-year meeting - TBD
E117: =CONCATENATE("End-of-year meeting - ", TEXT($F$11,"dd/mm/yyyy")) -> End-of-year meeting - TBD
F118: =F7 -> Anael
F119: % accomplished | H119: Comments
E120: =CONCATENATE("Mid-year meeting - ", TEXT($F$10,"dd/mm/yyyy")) -> Mid-year meeting - TBD
E121: =CONCATENATE("End-of-year meeting - ", TEXT($F$11,"dd/mm/yyyy")) -> End-of-year meeting - TBD
F122: GOAL 4
E123: Short description | F123: ='CC 2024'!F123 -> Investigate how a chatbot / AI can help NOC operations
E124: Make it SMART | F124: Specific | I124: Measurable | J124: Achievable | K124: Relevant | L124: Time-bound
F125: ='CC 2024'!F125 -> Based on the ticket information, NRMS data, Stats portal data, identify and suggest how AI/Chatbot can help daily operations of the NOC / Service Delivery | I125: ='CC 2024'!I125 -> prototype delivered to Anael / roadmap ready to be implemented in 2025 | J125: ='CC 2024'!J125 -> thanks to Exploration / gather Akshat researchs | K125: ='CC 2024'!K125 -> To facilitate NOC / Service delivery gathering of information | L125: ='CC 2024'!L125 -> Q4 2024 | O125: =IF(L125="Fails to meet objective", 4, IF(L125="Partially meets objective", 3, IF(L125="Meets expectations", 2, IF(L125="Exceeds expectations", 1,IF(L125="To be done", ""))))) -> FALSE
F126: ='CC 2023'!E2 -> Employee Name
F127: % accomplished | H127: Comments
E128: =CONCATENATE("Mid-year meeting - ", TEXT($F$10,"dd/mm/yyyy")) -> Mid-year meeting - TBD
E129: =CONCATENATE("End-of-year meeting - ", TEXT($F$11,"dd/mm/yyyy")) -> End-of-year meeting - TBD
F130: =F7 -> Anael
F131: % accomplished | H131: Comments
E132: =CONCATENATE("Mid-year meeting - ", TEXT($F$10,"dd/mm/yyyy")) -> Mid-year meeting - TBD
E133: =CONCATENATE("End-of-year meeting - ", TEXT($F$11,"dd/mm/yyyy")) -> End-of-year meeting - TBD
F134: GOAL 5
E135: Short description | F135: ='CC 2024'!F135 -> Deliver on User Requests
E136: Make it SMART | F136: Specific | I136: Measurable | J136: Achievable | K136: Relevant | L136: Time-bound
F137: ='CC 2024'!F137 -> To be able to support Eng, NOC, Service Delivery teams new feature requests and support existing systems | I137: ='CC 2024'!I137 -> 1-100 % New feature requests implemented 2- support - No major concern raised by relevant teams & most of the issues should get fixed within resonable timeframes | J137: ='CC 2024'!J137 -> Yes, after knowledge transfer | K137: ='CC 2024'!K137 -> To be able to maintain existing resources managed by Dev Team | L137: ='CC 2024'!L137 -> Q2 2024 | O137: =IF(L137="Fails to meet objective", 4, IF(L137="Partially meets objective", 3, IF(L137="Meets expectations", 2, IF(L137="Exceeds expectations", 1,IF(L137="To be done", ""))))) -> FALSE
F138: ='CC 2023'!E2 -> Employee Name
F139: % accomplished | H139: Comments
E140: =CONCATENATE("Mid-year meeting - ", TEXT($F$10,"dd/mm/yyyy")) -> Mid-year meeting - TBD
...

Sheet CC 2026
E2: ='CC 2023'!E2 -> Employee Name | L2: =CONCATENATE(G146,"/",Q174) -> #DIV/0!
E3: 2025
E4: Part 1: Ice Breaker : Introduction & General Feedback
E6: Role: | F6: ='CC 2025'!F6 -> Full Stack Developer
E7: Reports to: | F7: ='CC 2025'!F7 -> Anael
E8: Start Date: | F8: ='CC 2025'!F8 -> 45475
E10: Mid-year meeting | F10: TBD
E11: End-of-year meeting | F11: TBD
E14: How do you feel? Any ideas for BWD to improve ? | G14: ='CC 2023'!E2 -> Employee Name | L14: out of 10
E15: =CONCATENATE("Mid-year meeting - ", TEXT($F$10,"dd/mm/yyyy")) -> Mid-year meeting - TBD | F15: What is going well in my role
F16: What is challenging in my role
F17: How is BWD as an Employer ( management style, culture, work environment)
F18: Average | G18: =AVERAGE(L15:L17) -> #DIV/0!
E19: =CONCATENATE("End-of-year meeting - ", TEXT($F$11,"dd/mm/yyyy")) -> End-of-year meeting - TBD | F19: What is going well
F20: What is challenging
F21: How is BWD as an Employer ( management style, culture, work environment)
F22: Average | G22: =AVERAGE(L19:L21) -> #DIV/0!
E25: Part 2: Your skill set & Learning Plan
E26: Just checking your current skill-set and exploring new competences to develop.
E28: SKILL 1 | F28: ='CC 2025'!F28 -> Technology – Spring Boot, Java , MySQL , Graph DB , Docker, Groovy, Node.js , Angular , SQL, Unix , shell scripts
E29: =CONCATENATE("Mid-year meeting - ", TEXT($F$10,"dd/mm/yyyy")) -> Mid-year meeting - TBD | G29: ='CC 2023'!E2 -> Employee Name | J29: =F7 -> Anael
E31: =CONCATENATE("End-of-year meeting - ", TEXT($F$11,"dd/mm/yyyy")) -> End-of-year meeting - TBD | G31: ='CC 2023'!E2 -> Employee Name | J31: =F7 -> Anael
E34: SKILL 2 | F34: ='CC 2025'!F34 -> Tools - Grafana, GitLab, Jenkins , Confluence , OTRS , JIRA, OpenNMS , MariaDb , Postgres DB
E35: =CONCATENATE("Mid-year meeting - ", TEXT($F$10,"dd/mm/yyyy")) -> Mid-year meeting - TBD | G35: ='CC 2023'!E2 -> Employee Name | J35: =F7 -> Anael
E37: =CONCATENATE("End-of-year meeting - ", TEXT($F$11,"dd/mm/yyyy")) -> End-of-year meeting - TBD | G37: ='CC 2023'!E2 -> Employee Name | J37: =F7 -> Anael
E40: SKILL 3 | F40: ='CC 2025'!F40 -> Integration – Pentahu
E41: =CONCATENATE("Mid-year meeting - ", TEXT($F$10,"dd/mm/yyyy")) -> Mid-year meeting - TBD | G41: ='CC 2023'!E2 -> Employee Name | J41: =F7 -> Anael
E43: =CONCATENATE("End-of-year meeting - ", TEXT($F$11,"dd/mm/yyyy")) -> End-of-year meeting - TBD | G43: ='CC 2023'!E2 -> Employee Name | J43: =F7 -> Anael
E46: SKILL 4 | F46: ='CC 2025'!F46 -> 0
E47: =CONCATENATE("Mid-year meeting - ", TEXT($F$10,"dd/mm/yyyy")) -> Mid-year meeting - TBD | G47: ='CC 2023'!E2 -> Employee Name | J47: =F7 -> Anael
E49: =CONCATENATE("End-of-year meeting - ", TEXT($F$11,"dd/mm/yyyy")) -> End-of-year meeting - TBD | G49: ='CC 2023'!E2 -> Employee Name | J49: =F7 -> Anael
E52: SKILL 5 | F52: ='CC 2025'!F52 -> 0
E53: =CONCATENATE("Mid-year meeting - ", TEXT($F$10,"dd/mm/yyyy")) -> Mid-year meeting - TBD | G53: ='CC 2023'!E2 -> Employee Name | J53: =F7 -> Anael
E55: =CONCATENATE("End-of-year meeting - ", TEXT($F$11,"dd/mm/yyyy")) -> End-of-year meeting - TBD | G55: ='CC 2023'!E2 -> Employee Name | J55: =F7 -> Anael
E58: SKILL 6 | F58: ='CC 2025'!F58 -> 0
E59: =CONCATENATE("Mid-year meeting - ", TEXT($F$10,"dd/mm/yyyy")) -> Mid-year meeting - TBD | G59: ='CC 2023'!E2 -> Employee Name | J59: =F7 -> Anael
E61: =CONCATENATE("End-of-year meeting - ", TEXT($F$11,"dd/mm/yyyy")) -> End-of-year meeting - TBD | G61: ='CC 2023'!E2 -> Employee Name | J61: =F7 -> Anael
E64: SKILL 7 | F64: ='CC 2025'!F64 -> 0
E65: =CONCATENATE("Mid-year meeting - ", TEXT($F$10,"dd/mm/yyyy")) -> Mid-year meeting - TBD | G65: ='CC 2023'!E2 -> Employee Name | J65: =F7 -> Anael
E67: =CONCATENATE("End-of-year meeting - ", TEXT($F$11,"dd/mm/yyyy")) -> End-of-year meeting - TBD | G67: ='CC 2023'!E2 -> Employee Name | J67: =F7 -> Anael
E71: Based on your skill-set and growth plan, what is your learning target? Plan, Track, Celebrate!
E72: Training required (description, link) | G72: Format | H72: Timeline | I72: Budget | J72: Supported by BWD? | K72: % of accomplishment | L72: Training's review (/10)
E83: Part 3: SMART Goals
E84: With the help of your manager, and based on your current KPIs and ambition, define 5 SMART goals that you will accomplish for the next 12 months. The most significant will be included in your next year KPIs and used for your bonus calculation. No worries, if a goal is not applicable anymore, just do not fill a percentage and it will not be taken into account.
E85: Feeling lost? Check out this link -> | G85: Examples of SMART Goals
F86: GOAL1
E87: Short description | F87: ='CC 2025'!F87 -> Support container architecture
E88: Make it SMART | F88: Specific | I88: Measurable | J88: Achievable | K88: Relevant | L88: Time-bound
F89: ='CC 2025'!F89 -> Be proficient on troubleshooting the newly migrated servers onto containers. | I89: ='CC 2025'!I89 -> Be able to fix issues | J89: ='CC 2025'!J89 -> With Akshat knowledge transfer | K89: ='CC 2025'!K89 -> We need a ressource able to maintain this when Akshat has left. | L89: ='CC 2025'!L89 -> By 31/05/2024 | O89: =IF(L89="Fails to meet objective", 4, IF(L89="Partially meets objective", 3, IF(L89="Meets expectations", 2, IF(L89="Exceeds expectations", 1,IF(L89="To be done", ""))))) -> FALSE
F90: ='CC 2023'!E2 -> Employee Name
F91: % accomplished | H91: Comments
E92: =CONCATENATE("Mid-year meeting - ", TEXT($F$10,"dd/mm/yyyy")) -> Mid-year meeting - TBD
E93: =CONCATENATE("End-of-year meeting - ", TEXT($F$11,"dd/mm/yyyy")) -> End-of-year meeting - TBD
F94: =F7 -> Anael
F95: % accomplished | H95: Comments
E96: =CONCATENATE("Mid-year meeting - ", TEXT($F$10,"dd/mm/yyyy")) -> Mid-year meeting - TBD
E97: =CONCATENATE("End-of-year meeting - ", TEXT($F$11,"dd/mm/yyyy")) -> End-of-year meeting - TBD
F98: GOAL 2
E99: Short description | F99: ='CC 2025'!F99 -> Improve NRMS usability
E100: Make it SMART | F100: Specific | I100: Measurable | J100: Achievable | K100: Relevant | L100: Time-bound
F101: ='CC 2025'!F101 -> In collaboration with NOC and Thasa, evaluate, prioritize, and improve features/GUI to make NRMS more user friendly. | I101: ='CC 2025'!I101 -> Based on targets defined by Thasa/NOC | J101: ='CC 2025'!J101 -> With support of NOC & Thasa | K101: ='CC 2025'!K101 -> NRMS is our primary tool to manage ressources and it must be "sexy" to use. | L101: ='CC 2025'!L101 -> Q3 2024 | O101: =IF(L101="Fails to meet objective", 4, IF(L101="Partially meets objective", 3, IF(L101="Meets expectations", 2, IF(L101="Exceeds expectations", 1,IF(L101="To be done", ""))))) -> FALSE
F102: ='CC 2023'!E2 -> Employee Name
F103: % accomplished | H103: Comments
E104: =CONCATENATE("Mid-year meeting - ", TEXT($F$10,"dd/mm/yyyy")) -> Mid-year meeting - TBD
E105: =CONCATENATE("End-of-year meeting - ", TEXT($F$11,"dd/mm/yyyy")) -> End-of-year meeting - TBD
F106: =F7 -> Anael
F107: % accomplished | H107: Comments
E108: =CONCATENATE("Mid-year meeting - ", TEXT($F$10,"dd/mm/yyyy")) -> Mid-year meeting - TBD
E109: =CONCATENATE("End-of-year meeting - ", TEXT($F$11,"dd/mm/yyyy")) -> End-of-year meeting - TBD
F110: GOAL 3
E111: Short description | F111: ='CC 2025'!F111 -> Allow Service delivery team to provision new services on stats portal & NRMS
E112: Make it SMART | F112: Specific | I112: Measurable | J112: Achievable | K112: Relevant | L112: Time-bound
F113: ='CC 2025'!F113 -> Each time we onboard or remove a circuit/customer, IT-Dev is involved to manually create the entries in Stats portal, NRMS and Customer Portal. I'd like this process to be handled by Service Delivery team. | I113: ='CC 2025'!I113 -> 100% successfull usage by Service Delivery team | J113: ='CC 2025'!J113 -> by designing and implementing tool | K113: ='CC 2025'!K113 -> To reduce load on IT-DEV and allow SD to be autonomous | L113: ='CC 2025'!L113 -> Q4 2024 | O113: =IF(L113="Fails to meet objective", 4, IF(L113="Partially meets objective", 3, IF(L113="Meets expectations", 2, IF(L113="Exceeds expectations", 1,IF(L113="To be done", ""))))) -> FALSE
F114: ='CC 2023'!E2 -> Employee Name
F115: % accomplished | H115: Comments
E116: =CONCATENATE("Mid-year meeting - ", TEXT($F$10,"dd/mm/yyyy")) -> Mid-year meeting - TBD
E117: =CONCATENATE("End-of-year meeting - ", TEXT($F$11,"dd/mm/yyyy")) -> End-of-year meeting - TBD
F118: =F7 -> Anael
F119: % accomplished | H119: Comments
E120: =CONCATENATE("Mid-year meeting - ", TEXT($F$10,"dd/mm/yyyy")) -> Mid-year meeting - TBD
E121: =CONCATENATE("End-of-year meeting - ", TEXT($F$11,"dd/mm/yyyy")) -> End-of-year meeting - TBD
F122: GOAL 4
E123: Short description | F123: ='CC 2025'!F123 -> Investigate how a chatbot / AI can help NOC operations
E124: Make it SMART | F124: Specific | I124: Measurable | J124: Achievable | K124: Relevant | L124: Time-bound
F125: ='CC 2025'!F125 -> Based on the ticket information, NRMS data, Stats portal data, identify and suggest how AI/Chatbot can help daily operations of the NOC / Service Delivery | I125: ='CC 2025'!I125 -> prototype delivered to Anael / roadmap ready to be implemented in 2025 | J125: ='CC 2025'!J125 -> thanks to Exploration / gather Akshat researchs | K125: ='CC 2025'!K125 -> To facilitate NOC / Service delivery gathering of information | L125: ='CC 2025'!L125 -> Q4 2024 | O125: =IF(L125="Fails to meet objective", 4, IF(L125="Partially meets objective", 3, IF(L125="Meets expectations", 2, IF(L125="Exceeds expectations", 1,IF(L125="To be done", ""))))) -> FALSE
F126: ='CC 2023'!E2 -> Employee Name
F127: % accomplished | H127: Comments
E128: =CONCATENATE("Mid-year meeting - ", TEXT($F$10,"dd/mm/yyyy")) -> Mid-year meeting - TBD
E129: =CONCATENATE("End-of-year meeting - ", TEXT($F$11,"dd/mm/yyyy")) -> End-of-year meeting - TBD
F130: =F7 -> Anael
F131: % accomplished | H131: Comments
E132: =CONCATENATE("Mid-year meeting - ", TEXT($F$10,"dd/mm/yyyy")) -> Mid-year meeting - TBD
E133: =CONCATENATE("End-of-year meeting - ", TEXT($F$11,"dd/mm/yyyy")) -> End-of-year meeting - TBD
F134: GOAL 5
E135: Short description | F135: ='CC 2025'!F135 -> Deliver on User Requests
E136: Make it SMART | F136: Specific | I136: Measurable | J136: Achievable | K136: Relevant | L136: Time-bound
F137: ='CC 2025'!F137 -> To be able to support Eng, NOC, Service Delivery teams new feature requests and support existing systems | I137: ='CC 2025'!I137 -> 1-100 % New feature requests implemented 2- support - No major concern raised by relevant teams & most of the issues should get fixed within resonable timeframes | J137: ='CC 2025'!J137 -> Yes, after knowledge transfer | K137: ='CC 2025'!K137 -> To be able to maintain existing resources managed by Dev Team | L137: ='CC 2025'!L137 -> Q2 2024 | O137: =IF(L137="Fails to meet objective", 4, IF(L137="Partially meets objective", 3, IF(L137="Meets expectations", 2, IF(L137="Exceeds expectations", 1,IF(L137="To be done", ""))))) -> FALSE
F138: ='CC 2023'!E2 -> Employee Name
F139: % accomplished | H139: Comments
E140: =CONCATENATE("Mid-year meeting - ", TEXT($F$10,"dd/mm/yyyy")) -> Mid-year meeting - TBD
...

Sheet CC Model
E2: ='CC 2023'!E2 -> Employee Name | L2: =CONCATENATE(G146,"/",Q174) -> #DIV/0!
E3: 2023
E4: Part 1: Ice Breaker : Introduction & General Feedback
E6: Role:
E7: Reports to: | F7: Manager Name
E8: Start Date:
E10: Mid-year meeting | F10: TBD
E11: End-of-year meeting | F11: TBD
E14: How do you feel? Any ideas for BWD to improve ? | G14: ='CC 2023'!E2 -> Employee Name | L14: out of 10
E15: =CONCATENATE("Mid-year meeting - ", TEXT($F$10,"dd/mm/yyyy")) -> Mid-year meeting - TBD | F15: What is going well in my role
F16: What is challenging in my role
F17: How is BWD as an Employer ( management style, culture, work environment)
F18: Average | G18: =AVERAGE(L15:L17) -> #DIV/0!
E19: =CONCATENATE("End-of-year meeting - ", TEXT($F$11,"dd/mm/yyyy")) -> End-of-year meeting - TBD | F19: What is going well
F20: What is challenging
F21: How is BWD as an Employer ( management style, culture, work environment)
F22: Average | G22: =AVERAGE(L19:L21) -> #DIV/0!
E25: Part 2: Your skill set & Learning Plan
E26: Just checking your current skill-set and exploring new competences to develop.
E28: SKILL 1
E29: =CONCATENATE("Mid-year meeting - ", TEXT($F$10,"dd/mm/yyyy")) -> Mid-year meeting - TBD | G29: ='CC 2023'!E2 -> Employee Name | J29: =F7 -> Manager Name
E31: =CONCATENATE("End-of-year meeting - ", TEXT($F$11,"dd/mm/yyyy")) -> End-of-year meeting - TBD | G31: ='CC 2023'!E2 -> Employee Name | J31: =F7 -> Manager Name
E34: SKILL 2
E35: =CONCATENATE("Mid-year meeting - ", TEXT($F$10,"dd/mm/yyyy")) -> Mid-year meeting - TBD | G35: ='CC 2023'!E2 -> Employee Name | J35: =F7 -> Manager Name
E37: =CONCATENATE("End-of-year meeting - ", TEXT($F$11,"dd/mm/yyyy")) -> End-of-year meeting - TBD | G37: ='CC 2023'!E2 -> Employee Name | J37: =F7 -> Manager Name
E40: SKILL 3
E41: =CONCATENATE("Mid-year meeting - ", TEXT($F$10,"dd/mm/yyyy")) -> Mid-year meeting - TBD | G41: ='CC 2023'!E2 -> Employee Name | J41: =F7 -> Manager Name
E43: =CONCATENATE("End-of-year meeting - ", TEXT($F$11,"dd/mm/yyyy")) -> End-of-year meeting - TBD | G43: ='CC 2023'!E2 -> Employee Name | J43: =F7 -> Manager Name
E46: SKILL 4
E47: =CONCATENATE("Mid-year meeting - ", TEXT($F$10,"dd/mm/yyyy")) -> Mid-year meeting - TBD | G47: ='CC 2023'!E2 -> Employee Name | J47: =F7 -> Manager Name
E49: =CONCATENATE("End-of-year meeting - ", TEXT($F$11,"dd/mm/yyyy")) -> End-of-year meeting - TBD | G49: ='CC 2023'!E2 -> Employee Name | J49: =F7 -> Manager Name
E52: SKILL 5
E53: =CONCATENATE("Mid-year meeting - ", TEXT($F$10,"dd/mm/yyyy")) -> Mid-year meeting - TBD | G53: ='CC 2023'!E2 -> Employee Name | J53: =F7 -> Manager Name
E55: =CONCATENATE("End-of-year meeting - ", TEXT($F$11,"dd/mm/yyyy")) -> End-of-year meeting - TBD | G55: ='CC 2023'!E2 -> Employee Name | J55: =F7 -> Manager Name
E58: SKILL 6
E59: =CONCATENATE("Mid-year meeting - ", TEXT($F$10,"dd/mm/yyyy")) -> Mid-year meeting - TBD | G59: ='CC 2023'!E2 -> Employee Name | J59: =F7 -> Manager Name
E61: =CONCATENATE("End-of-year meeting - ", TEXT($F$11,"dd/mm/yyyy")) -> End-of-year meeting - TBD | G61: ='CC 2023'!E2 -> Employee Name | J61: =F7 -> Manager Name
E64: SKILL 7
E65: =CONCATENATE("Mid-year meeting - ", TEXT($F$10,"dd/mm/yyyy")) -> Mid-year meeting - TBD | G65: ='CC 2023'!E2 -> Employee Name | J65: =F7 -> Manager Name
E67: =CONCATENATE("End-of-year meeting - ", TEXT($F$11,"dd/mm/yyyy")) -> End-of-year meeting - TBD | G67: ='CC 2023'!E2 -> Employee Name | J67: =F7 -> Manager Name
E71: Based on your skill-set and growth plan, what is your learning target? Plan, Track, Celebrate!
E72: Training required (description, link) | G72: Format | H72: Timeline | I72: Budget | J72: Supported by BWD? | K72: % of accomplishment | L72: Training's review (/10)
E83: Part 3: SMART Goals
E84: With the help of your manager, and based on your current KPIs and ambition, define 5 SMART goals that you will accomplish for the next 12 months. The most significant will be included in your next year KPIs and used for your bonus calculation. No worries, if a goal is not applicable anymore, just do not fill a percentage and it will not be taken into account.
E85: Feeling lost? Check out this link -> | G85: Examples of SMART Goals
F86: GOAL1
E87: Short description
E88: Make it SMART | F88: Specific | I88: Measurable | J88: Achievable | K88: Relevant | L88: Time-bound
O89: =IF(L89="Fails to meet objective", 4, IF(L89="Partially meets objective", 3, IF(L89="Meets expectations", 2, IF(L89="Exceeds expectations", 1,IF(L89="To be done", ""))))) -> FALSE
F90: ='CC 2023'!E2 -> Employee Name
F91: % accomplished | H91: Comments
E92: =CONCATENATE("Mid-year meeting - ", TEXT($F$10,"dd/mm/yyyy")) -> Mid-year meeting - TBD
E93: =CONCATENATE("End-of-year meeting - ", TEXT($F$11,"dd/mm/yyyy")) -> End-of-year meeting - TBD
F94: =F7 -> Manager Name
F95: % accomplished | H95: Comments
E96: =CONCATENATE("Mid-year meeting - ", TEXT($F$10,"dd/mm/yyyy")) -> Mid-year meeting - TBD
E97: =CONCATENATE("End-of-year meeting - ", TEXT($F$11,"dd/mm/yyyy")) -> End-of-year meeting - TBD
F98: GOAL 2
E99: Short description
E100: Make it SMART | F100: Specific | I100: Measurable | J100: Achievable | K100: Relevant | L100: Time-bound
O101: =IF(L101="Fails to meet objective", 4, IF(L101="Partially meets objective", 3, IF(L101="Meets expectations", 2, IF(L101="Exceeds expectations", 1,IF(L101="To be done", ""))))) -> FALSE
F102: ='CC 2023'!E2 -> Employee Name
F103: % accomplished | H103: Comments
E104: =CONCATENATE("Mid-year meeting - ", TEXT($F$10,"dd/mm/yyyy")) -> Mid-year meeting - TBD
E105: =CONCATENATE("End-of-year meeting - ", TEXT($F$11,"dd/mm/yyyy")) -> End-of-year meeting - TBD
F106: =F7 -> Manager Name
F107: % accomplished | H107: Comments
E108: =CONCATENATE("Mid-year meeting - ", TEXT($F$10,"dd/mm/yyyy")) -> Mid-year meeting - TBD
E109: =CONCATENATE("End-of-year meeting - ", TEXT($F$11,"dd/mm/yyyy")) -> End-of-year meeting - TBD
F110: GOAL 3
E111: Short description
E112: Make it SMART | F112: Specific | I112: Measurable | J112: Achievable | K112: Relevant | L112: Time-bound
O113: =IF(L113="Fails to meet objective", 4, IF(L113="Partially meets objective", 3, IF(L113="Meets expectations", 2, IF(L113="Exceeds expectations", 1,IF(L113="To be done", ""))))) -> FALSE
F114: ='CC 2023'!E2 -> Employee Name
F115: % accomplished | H115: Comments
E116: =CONCATENATE("Mid-year meeting - ", TEXT($F$10,"dd/mm/yyyy")) -> Mid-year meeting - TBD
E117: =CONCATENATE("End-of-year meeting - ", TEXT($F$11,"dd/mm/yyyy")) -> End-of-year meeting - TBD
F118: =F7 -> Manager Name
F119: % accomplished | H119: Comments
E120: =CONCATENATE("Mid-year meeting - ", TEXT($F$10,"dd/mm/yyyy")) -> Mid-year meeting - TBD
E121: =CONCATENATE("End-of-year meeting - ", TEXT($F$11,"dd/mm/yyyy")) -> End-of-year meeting - TBD
F122: GOAL 4
E123: Short description
E124: Make it SMART | F124: Specific | I124: Measurable | J124: Achievable | K124: Relevant | L124: Time-bound
O125: =IF(L125="Fails to meet objective", 4, IF(L125="Partially meets objective", 3, IF(L125="Meets expectations", 2, IF(L125="Exceeds expectations", 1,IF(L125="To be done", ""))))) -> FALSE
F126: ='CC 2023'!E2 -> Employee Name
F127: % accomplished | H127: Comments
E128: =CONCATENATE("Mid-year meeting - ", TEXT($F$10,"dd/mm/yyyy")) -> Mid-year meeting - TBD
E129: =CONCATENATE("End-of-year meeting - ", TEXT($F$11,"dd/mm/yyyy")) -> End-of-year meeting - TBD
F130: =F7 -> Manager Name
F131: % accomplished | H131: Comments
E132: =CONCATENATE("Mid-year meeting - ", TEXT($F$10,"dd/mm/yyyy")) -> Mid-year meeting - TBD
E133: =CONCATENATE("End-of-year meeting - ", TEXT($F$11,"dd/mm/yyyy")) -> End-of-year meeting - TBD
F134: GOAL 5
E135: Short description
E136: Make it SMART | F136: Specific | I136: Measurable | J136: Achievable | K136: Relevant | L136: Time-bound
O137: =IF(L137="Fails to meet objective", 4, IF(L137="Partially meets objective", 3, IF(L137="Meets expectations", 2, IF(L137="Exceeds expectations", 1,IF(L137="To be done", ""))))) -> FALSE
F138: ='CC 2023'!E2 -> Employee Name
F139: % accomplished | H139: Comments
E140: =CONCATENATE("Mid-year meeting - ", TEXT($F$10,"dd/mm/yyyy")) -> Mid-year meeting - TBD
...

Sheet CC 2027
E2: ='CC 2023'!E2 -> Employee Name | L2: =CONCATENATE(G146,"/",Q174) -> #DIV/0!
E3: 2026
E4: Part 1: Ice Breaker : Introduction & General Feedback
E6: Role: | F6: ='CC 2026'!F6 -> Full Stack Developer
E7: Reports to: | F7: ='CC 2026'!F7 -> Anael
E8: Start Date: | F8: ='CC 2026'!F8 -> 45475
E10: Mid-year meeting | F10: TBD
E11: End-of-year meeting | F11: TBD
E14: How do you feel? Any ideas for BWD to improve ? | G14: ='CC 2023'!E2 -> Employee Name | L14: out of 10
E15: =CONCATENATE("Mid-year meeting - ", TEXT($F$10,"dd/mm/yyyy")) -> Mid-year meeting - TBD | F15: What is going well in my role
F16: What is challenging in my role
F17: How is BWD as an Employer ( management style, culture, work environment)
F18: Average | G18: =AVERAGE(L15:L17) -> #DIV/0!
E19: =CONCATENATE("End-of-year meeting - ", TEXT($F$11,"dd/mm/yyyy")) -> End-of-year meeting - TBD | F19: What is going well
F20: What is challenging
F21: How is BWD as an Employer ( management style, culture, work environment)
F22: Average | G22: =AVERAGE(L19:L21) -> #DIV/0!
E25: Part 2: Your skill set & Learning Plan
E26: Just checking your current skill-set and exploring new competences to develop.
E28: SKILL 1 | F28: ='CC 2026'!F28 -> Technology – Spring Boot, Java , MySQL , Graph DB , Docker, Groovy, Node.js , Angular , SQL, Unix , shell scripts
E29: =CONCATENATE("Mid-year meeting - ", TEXT($F$10,"dd/mm/yyyy")) -> Mid-year meeting - TBD | G29: ='CC 2023'!E2 -> Employee Name | J29: =F7 -> Anael
E31: =CONCATENATE("End-of-year meeting - ", TEXT($F$11,"dd/mm/yyyy")) -> End-of-year meeting - TBD | G31: ='CC 2023'!E2 -> Employee Name | J31: =F7 -> Anael
E34: SKILL 2 | F34: ='CC 2026'!F34 -> Tools - Grafana, GitLab, Jenkins , Confluence , OTRS , JIRA, OpenNMS , MariaDb , Postgres DB
E35: =CONCATENATE("Mid-year meeting - ", TEXT($F$10,"dd/mm/yyyy")) -> Mid-year meeting - TBD | G35: ='CC 2023'!E2 -> Employee Name | J35: =F7 -> Anael
E37: =CONCATENATE("End-of-year meeting - ", TEXT($F$11,"dd/mm/yyyy")) -> End-of-year meeting - TBD | G37: ='CC 2023'!E2 -> Employee Name | J37: =F7 -> Anael
E40: SKILL 3 | F40: ='CC 2026'!F40 -> Integration – Pentahu
E41: =CONCATENATE("Mid-year meeting - ", TEXT($F$10,"dd/mm/yyyy")) -> Mid-year meeting - TBD | G41: ='CC 2023'!E2 -> Employee Name | J41: =F7 -> Anael
E43: =CONCATENATE("End-of-year meeting - ", TEXT($F$11,"dd/mm/yyyy")) -> End-of-year meeting - TBD | G43: ='CC 2023'!E2 -> Employee Name | J43: =F7 -> Anael
E46: SKILL 4 | F46: ='CC 2026'!F46 -> 0
E47: =CONCATENATE("Mid-year meeting - ", TEXT($F$10,"dd/mm/yyyy")) -> Mid-year meeting - TBD | G47: ='CC 2023'!E2 -> Employee Name | J47: =F7 -> Anael
E49: =CONCATENATE("End-of-year meeting - ", TEXT($F$11,"dd/mm/yyyy")) -> End-of-year meeting - TBD | G49: ='CC 2023'!E2 -> Employee Name | J49: =F7 -> Anael
E52: SKILL 5 | F52: ='CC 2026'!F52 -> 0
E53: =CONCATENATE("Mid-year meeting - ", TEXT($F$10,"dd/mm/yyyy")) -> Mid-year meeting - TBD | G53: ='CC 2023'!E2 -> Employee Name | J53: =F7 -> Anael
E55: =CONCATENATE("End-of-year meeting - ", TEXT($F$11,"dd/mm/yyyy")) -> End-of-year meeting - TBD | G55: ='CC 2023'!E2 -> Employee Name | J55: =F7 -> Anael
E58: SKILL 6 | F58: ='CC 2026'!F58 -> 0
E59: =CONCATENATE("Mid-year meeting - ", TEXT($F$10,"dd/mm/yyyy")) -> Mid-year meeting - TBD | G59: ='CC 2023'!E2 -> Employee Name | J59: =F7 -> Anael
E61: =CONCATENATE("End-of-year meeting - ", TEXT($F$11,"dd/mm/yyyy")) -> End-of-year meeting - TBD | G61: ='CC 2023'!E2 -> Employee Name | J61: =F7 -> Anael
E64: SKILL 7 | F64: ='CC 2026'!F64 -> 0
E65: =CONCATENATE("Mid-year meeting - ", TEXT($F$10,"dd/mm/yyyy")) -> Mid-year meeting - TBD | G65: ='CC 2023'!E2 -> Employee Name | J65: =F7 -> Anael
E67: =CONCATENATE("End-of-year meeting - ", TEXT($F$11,"dd/mm/yyyy")) -> End-of-year meeting - TBD | G67: ='CC 2023'!E2 -> Employee Name | J67: =F7 -> Anael
E71: Based on your skill-set and growth plan, what is your learning target? Plan, Track, Celebrate!
E72: Training required (description, link) | G72: Format | H72: Timeline | I72: Budget | J72: Supported by BWD? | K72: % of accomplishment | L72: Training's review (/10)
E83: Part 3: SMART Goals
E84: With the help of your manager, and based on your current KPIs and ambition, define 5 SMART goals that you will accomplish for the next 12 months. The most significant will be included in your next year KPIs and used for your bonus calculation. No worries, if a goal is not applicable anymore, just do not fill a percentage and it will not be taken into account.
E85: Feeling lost? Check out this link -> | G85: Examples of SMART Goals
F86: GOAL1
E87: Short description
E88: Make it SMART | F88: Specific | I88: Measurable | J88: Achievable | K88: Relevant | L88: Time-bound
O89: =IF(L89="Fails to meet objective", 4, IF(L89="Partially meets objective", 3, IF(L89="Meets expectations", 2, IF(L89="Exceeds expectations", 1,IF(L89="To be done", ""))))) -> FALSE
F90: ='CC 2023'!E2 -> Employee Name
F91: % accomplished | H91: Comments
E92: =CONCATENATE("Mid-year meeting - ", TEXT($F$10,"dd/mm/yyyy")) -> Mid-year meeting - TBD
E93: =CONCATENATE("End-of-year meeting - ", TEXT($F$11,"dd/mm/yyyy")) -> End-of-year meeting - TBD
F94: =F7 -> Anael
F95: % accomplished | H95: Comments
E96: =CONCATENATE("Mid-year meeting - ", TEXT($F$10,"dd/mm/yyyy")) -> Mid-year meeting - TBD
E97: =CONCATENATE("End-of-year meeting - ", TEXT($F$11,"dd/mm/yyyy")) -> End-of-year meeting - TBD
F98: GOAL 2
E99: Short description
E100: Make it SMART | F100: Specific | I100: Measurable | J100: Achievable | K100: Relevant | L100: Time-bound
O101: =IF(L101="Fails to meet objective", 4, IF(L101="Partially meets objective", 3, IF(L101="Meets expectations", 2, IF(L101="Exceeds expectations", 1,IF(L101="To be done", ""))))) -> FALSE
F102: ='CC 2023'!E2 -> Employee Name
F103: % accomplished | H103: Comments
E104: =CONCATENATE("Mid-year meeting - ", TEXT($F$10,"dd/mm/yyyy")) -> Mid-year meeting - TBD
E105: =CONCATENATE("End-of-year meeting - ", TEXT($F$11,"dd/mm/yyyy")) -> End-of-year meeting - TBD
F106: =F7 -> Anael
F107: % accomplished | H107: Comments
E108: =CONCATENATE("Mid-year meeting - ", TEXT($F$10,"dd/mm/yyyy")) -> Mid-year meeting - TBD
E109: =CONCATENATE("End-of-year meeting - ", TEXT($F$11,"dd/mm/yyyy")) -> End-of-year meeting - TBD
F110: GOAL 3
E111: Short description
E112: Make it SMART | F112: Specific | I112: Measurable | J112: Achievable | K112: Relevant | L112: Time-bound
O113: =IF(L113="Fails to meet objective", 4, IF(L113="Partially meets objective", 3, IF(L113="Meets expectations", 2, IF(L113="Exceeds expectations", 1,IF(L113="To be done", ""))))) -> FALSE
F114: ='CC 2023'!E2 -> Employee Name
F115: % accomplished | H115: Comments
E116: =CONCATENATE("Mid-year meeting - ", TEXT($F$10,"dd/mm/yyyy")) -> Mid-year meeting - TBD
E117: =CONCATENATE("End-of-year meeting - ", TEXT($F$11,"dd/mm/yyyy")) -> End-of-year meeting - TBD
F118: =F7 -> Anael
F119: % accomplished | H119: Comments
E120: =CONCATENATE("Mid-year meeting - ", TEXT($F$10,"dd/mm/yyyy")) -> Mid-year meeting - TBD
E121: =CONCATENATE("End-of-year meeting - ", TEXT($F$11,"dd/mm/yyyy")) -> End-of-year meeting - TBD
F122: GOAL 4
E123: Short description
E124: Make it SMART | F124: Specific | I124: Measurable | J124: Achievable | K124: Relevant | L124: Time-bound
O125: =IF(L125="Fails to meet objective", 4, IF(L125="Partially meets objective", 3, IF(L125="Meets expectations", 2, IF(L125="Exceeds expectations", 1,IF(L125="To be done", ""))))) -> FALSE
F126: ='CC 2023'!E2 -> Employee Name
F127: % accomplished | H127: Comments
E128: =CONCATENATE("Mid-year meeting - ", TEXT($F$10,"dd/mm/yyyy")) -> Mid-year meeting - TBD
E129: =CONCATENATE("End-of-year meeting - ", TEXT($F$11,"dd/mm/yyyy")) -> End-of-year meeting - TBD
F130: =F7 -> Anael
F131: % accomplished | H131: Comments
E132: =CONCATENATE("Mid-year meeting - ", TEXT($F$10,"dd/mm/yyyy")) -> Mid-year meeting - TBD
E133: =CONCATENATE("End-of-year meeting - ", TEXT($F$11,"dd/mm/yyyy")) -> End-of-year meeting - TBD
F134: GOAL 5
E135: Short description
E136: Make it SMART | F136: Specific | I136: Measurable | J136: Achievable | K136: Relevant | L136: Time-bound
O137: =IF(L137="Fails to meet objective", 4, IF(L137="Partially meets objective", 3, IF(L137="Meets expectations", 2, IF(L137="Exceeds expectations", 1,IF(L137="To be done", ""))))) -> FALSE
F138: ='CC 2023'!E2 -> Employee Name
F139: % accomplished | H139: Comments
E140: =CONCATENATE("Mid-year meeting - ", TEXT($F$10,"dd/mm/yyyy")) -> Mid-year meeting - TBD
...

Sheet Dashboard
A1: =TODAY() -> 45443
C5: Dashboard - Career Conversations
C6: Note: Some rows for future years are hidden. Unhide them when needed.
C7: ='CC 2023'!E2 -> Employee Name
C8: =YEAR(A1) -> 2024
D9: Our Vision | E9: We connect countries across oceans sustainably
D10: Our Mission | E10: We develop, fund and operate digital infrastructures in the Asia-Pacific region
D11: Our Values | E11: Quality, Innovation, Collaboration, Customer centricity
D13: My Mission What is your very own purpose?
D16: Start - Stop - Continue
D18: Date | E18: Start | F18: Stop | G18: Continue
D19: 2023 | E19: =CONCATENATE('CC 2023'!$F$187, " | ", 'CC 2023'!$F$188) -> | | F19: =CONCATENATE('CC 2023'!$H$187, " | ", 'CC 2023'!$H$188) -> | | G19: =CONCATENATE('CC 2023'!$K$187, " | ", 'CC 2023'!$K$188) -> |
D20: 2024 | E20: =CONCATENATE('CC 2024'!$F$187, " | ", 'CC 2024'!$F$188) -> | | F20: =CONCATENATE('CC 2024'!$H$187, " | ", 'CC 2024'!$H$188) -> | | G20: =CONCATENATE('CC 2024'!$K$187, " | ", 'CC 2024'!$K$188) -> |
D21: 2025 | E21: =CONCATENATE('CC 2025'!$F$187, " | ", 'CC 2025'!$F$188) -> | | F21: =CONCATENATE('CC 2025'!$H$187, " | ", 'CC 2025'!$H$188) -> | | G21: =CONCATENATE('CC 2025'!$K$187, " | ", 'CC 2025'!$K$188) -> |
D22: 2026 | E22: =CONCATENATE('CC 2026'!$F$187, " | ", 'CC 2026'!$F$188) -> | | F22: =CONCATENATE('CC 2026'!$H$187, " | ", 'CC 2026'!$H$188) -> | | G22: =CONCATENATE('CC 2026'!$K$187, " | ", 'CC 2026'!$K$188) -> |
D23: 2027 | E23: =CONCATENATE('CC 2027'!$F$187, " | ", 'CC 2027'!$F$188) -> | | F23: =CONCATENATE('CC 2027'!$H$187, " | ", 'CC 2027'!$H$188) -> | | G23: =CONCATENATE('CC 2027'!$K$187, " | ", 'CC 2027'!$K$188) -> |
D27: SMART Goals
D29: Date | E29: Description | F29: Team member status | G29: Manager status
D30: 2023 | E30: ='CC 2023'!$F$87 -> Talent Acquisition ( 100% fast & successful recruitments ) 2023 | F30: =MAX('CC 2023'!$F$92:$G$93) -> 0 | G30: =MAX('CC 2023'!$F$96:$G$97) -> 0
D31: 2023 | E31: ='CC 2023'!$F$99 -> 0 | F31: =MAX('CC 2023'!$F$104:$G$105) -> 0 | G31: =MAX('CC 2023'!$F$108:$G$109) -> 0
D32: 2023 | E32: ='CC 2023'!$F111 -> 0 | F32: =MAX('CC 2023'!$F$116:$G$117) -> 0 | G32: =MAX('CC 2023'!$F$120:$G$121) -> 0
D33: 2023 | E33: ='CC 2023'!$F$123 -> 0 | F33: =MAX('CC 2023'!$F$128:$G$129) -> 0 | G33: =MAX('CC 2023'!$F$132:$G$133) -> 0
D34: 2023 | E34: ='CC 2023'!$F$135 -> 0 | F34: =MAX('CC 2023'!$F$140:$G$141) -> 0 | G34: =MAX('CC 2023'!$F$144:$G$145) -> 0
D35: 2024 | F35: =MAX('CC 2024'!$F$92:$G$93) -> 0 | G35: =MAX('CC 2024'!$F$96:$G$97) -> 0
D36: 2024 | E36: ='CC 2024'!$F$99 -> Improve NRMS usability | F36: =MAX('CC 2024'!$F$104:$G$105) -> 0 | G36: =MAX('CC 2024'!$F$108:$G$109) -> 0
D37: 2024 | E37: ='CC 2024'!$F116 -> 0 | F37: =MAX('CC 2024'!$F$116:$G$117) -> 0 | G37: =MAX('CC 2024'!$F$120:$G$121) -> 0
D38: 2024 | E38: ='CC 2024'!$F$123 -> Investigate how a chatbot / AI can help NOC operations | F38: =MAX('CC 2024'!$F$128:$G$129) -> 0 | G38: =MAX('CC 2024'!$F$132:$G$133) -> 0
D39: 2024 | E39: ='CC 2024'!$F$135 -> Deliver on User Requests | F39: =MAX('CC 2024'!$F$140:$G$141) -> 0 | G39: =MAX('CC 2024'!$F$144:$G$145) -> 0
D40: 2025 | E40: ='CC 2025'!$F$87 -> Support container architecture | F40: =MAX('CC 2025'!$F$92:$G$93) -> 0 | G40: =MAX('CC 2025'!$F$96:$G$97) -> 0
D41: 2025 | E41: ='CC 2025'!$F$99 -> Improve NRMS usability | F41: =MAX('CC 2025'!$F$104:$G$105) -> 0 | G41: =MAX('CC 2025'!$F$108:$G$109) -> 0
D42: 2025 | E42: ='CC 2025'!$F121 -> 0 | F42: =MAX('CC 2025'!$F$116:$G$117) -> 0 | G42: =MAX('CC 2025'!$F$120:$G$121) -> 0
D43: 2025 | E43: ='CC 2025'!$F$123 -> Investigate how a chatbot / AI can help NOC operations | F43: =MAX('CC 2025'!$F$128:$G$129) -> 0 | G43: =MAX('CC 2025'!$F$132:$G$133) -> 0
D44: 2025 | E44: ='CC 2025'!$F$135 -> Deliver on User Requests | F44: =MAX('CC 2025'!$F$140:$G$141) -> 0 | G44: =MAX('CC 2025'!$F$144:$G$145) -> 0
D45: 2026 | E45: ='CC 2026'!$F$87 -> Support container architecture | F45: =MAX('CC 2026'!$F$92:$G$93) -> 0 | G45: =MAX('CC 2026'!$F$96:$G$97) -> 0
D46: 2026 | E46: ='CC 2026'!$F$99 -> Improve NRMS usability | F46: =MAX('CC 2026'!$F$104:$G$105) -> 0 | G46: =MAX('CC 2026'!$F$108:$G$109) -> 0
D47: 2026 | E47: ='CC 2026'!$F126 -> Employee Name | F47: =MAX('CC 2026'!$F$116:$G$117) -> 0 | G47: =MAX('CC 2026'!$F$120:$G$121) -> 0
D48: 2026 | E48: ='CC 2026'!$F$123 -> Investigate how a chatbot / AI can help NOC operations | F48: =MAX('CC 2026'!$F$128:$G$129) -> 0 | G48: =MAX('CC 2026'!$F$132:$G$133) -> 0
D49: 2026 | E49: ='CC 2026'!$F$135 -> Deliver on User Requests | F49: =MAX('CC 2026'!$F$140:$G$141) -> 0 | G49: =MAX('CC 2026'!$F$144:$G$145) -> 0
D50: 2027 | E50: ='CC 2027'!$F$87 -> 0 | F50: =MAX('CC 2027'!$F$92:$G$93) -> 0 | G50: =MAX('CC 2027'!$F$96:$G$97) -> 0
D51: 2027 | E51: ='CC 2027'!$F$99 -> 0 | F51: =MAX('CC 2027'!$F$104:$G$105) -> 0 | G51: =MAX('CC 2027'!$F$108:$G$109) -> 0
D52: 2027 | E52: ='CC 2027'!$F131 -> % accomplished | F52: =MAX('CC 2027'!$F$116:$G$117) -> 0 | G52: =MAX('CC 2027'!$F$120:$G$121) -> 0
D53: 2027 | E53: ='CC 2027'!$F$123 -> 0 | F53: =MAX('CC 2027'!$F$128:$G$129) -> 0 | G53: =MAX('CC 2027'!$F$132:$G$133) -> 0
D54: 2027 | E54: ='CC 2027'!$F$135 -> 0 | F54: =MAX('CC 2027'!$F$140:$G$141) -> 0 | G54: =MAX('CC 2027'!$F$144:$G$145) -> 0
F57: Parameters are hidden between those cells. Color the front and you will be able to see them.
F58: Column P-W | P58: Faible | Q58: 33.33
P59: Correct | Q59: 33.33
P60: Satisfaisant | Q60: 33.33 | U60: =INDEX(Table4[Manager], MATCH(YEAR(TODAY()), Table4[Year], 0)) -> #DIV/0!
P61: Vide | Q61: 100 | U61: Year | V61: Team member | W61: Manager
U62: 2023 | V62: =AVERAGEIF(F30:F34,"<>0") -> #DIV/0! | W62: =AVERAGEIF(G30:G34,"<>0") -> #DIV/0!
P63: Valeur indicateur | Q63: =120*U60 -> #DIV/0! | U63: 2024 | V63: =AVERAGEIF(F35:F39,"<>0") -> #DIV/0! | W63: =AVERAGEIF(G35:G39,"<>0") -> #DIV/0!
P64: Valeur indicateur | Q64: 2 | U64: 2025 | V64: =AVERAGEIF(F40:F44,"<>0") -> #DIV/0! | W64: =AVERAGEIF(G40:G44,"<>0") -> #DIV/0!
P65: Reste | Q65: 123 | U65: 2026 | V65: =AVERAGEIF(F45:F49,"<>0") -> #DIV/0! | W65: =AVERAGEIF(G45:G49,"<>0") -> #DIV/0!
U66: 2027 | V66: =AVERAGEIF(F50:F54,"<>0") -> #DIV/0! | W66: =AVERAGEIF(G50:G54,"<>0") -> #DIV/0!
D67: Values - End of year ratings
D69: Date | E69: Quality | F69: Innovation | G69: Collab | H69: Cust. Centricity
D70: 2023 | E70: =MAX('CC 2023'!$F$155:$F$157) -> 0 | F70: =MAX('CC 2023'!$F$160:$F$162) -> 0 | G70: =MAX('CC 2023'!$F$165:$F$167) -> 0 | H70: =MAX('CC 2023'!$F$170:$F$172) -> 0
D71: 2024 | E71: =MAX('CC 2024'!$F$155:$F$157) -> 0 | F71: =MAX('CC 2024'!$F$160:$F$162) -> 0 | G71: =MAX('CC 2024'!$F$165:$F$167) -> 0 | H71: =MAX('CC 2024'!$F$170:$F$172) -> 0
D72: 2025 | E72: =MAX('CC 2025'!$F$155:$F$157) -> 0 | F72: =MAX('CC 2025'!$F$160:$F$162) -> 0 | G72: =MAX('CC 2025'!$F$165:$F$167) -> 0 | H72: =MAX('CC 2025'!$F$170:$F$172) -> 0
D73: 2026 | E73: =MAX('CC 2026'!$F$155:$F$157) -> 0 | F73: =MAX('CC 2026'!$F$160:$F$162) -> 0 | G73: =MAX('CC 2026'!$F$165:$F$167) -> 0 | H73: =MAX('CC 2026'!$F$170:$F$172) -> 0
D74: 2027 | E74: =MAX('CC 2027'!$F$155:$F$157) -> 0 | F74: =MAX('CC 2027'!$F$160:$F$162) -> 0 | G74: =MAX('CC 2027'!$F$165:$F$167) -> 0 | H74: =MAX('CC 2027'!$F$170:$F$172) -> 0
D80: Trainings
D82: Date | E82: Name | F82: % achieved
D83: 2023 | E83: ='CC 2023'!$E$73 -> 0 | F83: ='CC 2023'!$K$73 -> 0
D84: 2023 | E84: ='CC 2023'!$E$74 -> 0 | F84: ='CC 2023'!$J$74 -> 0
D85: 2023 | E85: ='CC 2023'!$E$75 -> 0 | F85: ='CC 2023'!$K$75 -> 0
D86: 2023 | E86: ='CC 2023'!$E$76 -> 0 | F86: ='CC 2023'!$K$76 -> 0
D87: 2023 | E87: ='CC 2023'!$E$77 -> 0 | F87: ='CC 2023'!$K$77 -> 0
D88: 2023 | E88: ='CC 2023'!$E$78 -> 0 | F88: ='CC 2023'!$K$78 -> 0
D89: 2023 | E89: ='CC 2023'!$E$79 -> 0 | F89: ='CC 2023'!$K$79 -> 0
D90: 2023 | E90: ='CC 2023'!$E$80 -> 0 | F90: ='CC 2023'!$K$80 -> 0
D91: 2024 | E91: ='CC 2024'!$E$73 -> 0 | F91: ='CC 2024'!$K$73 -> 0
D92: 2024 | E92: ='CC 2024'!$E$74 -> 0 | F92: ='CC 2024'!$K$74 -> 0
D93: 2024 | E93: ='CC 2024'!$E$75 -> 0 | F93: ='CC 2024'!$K$75 -> 0
D94: 2024 | E94: ='CC 2024'!$E$76 -> 0 | F94: ='CC 2024'!$K$76 -> 0
D95: 2024 | E95: ='CC 2024'!$E$77 -> 0 | F95: ='CC 2024'!$K$77 -> 0
D96: 2024 | E96: ='CC 2024'!$E$78 -> 0 | F96: ='CC 2024'!$K$78 -> 0
D97: 2024 | E97: ='CC 2024'!$E$79 -> 0 | F97: ='CC 2024'!$K$79 -> 0
D98: 2024 | E98: ='CC 2024'!$E$80 -> 0 | F98: ='CC 2024'!$K$80 -> 0
D99: 2025 | E99: ='CC 2025'!$E$73 -> 0 | F99: ='CC 2025'!$K$73 -> 0
D100: 2025 | E100: ='CC 2025'!$E$74 -> 0 | F100: ='CC 2025'!$K$74 -> 0
D101: 2025 | E101: ='CC 2025'!$E$75 -> 0 | F101: ='CC 2025'!$K$75 -> 0
D102: 2025 | E102: ='CC 2025'!$E$76 -> 0 | F102: ='CC 2025'!$K$76 -> 0
D103: 2025 | E103: ='CC 2025'!$E$77 -> 0 | F103: ='CC 2025'!$K$77 -> 0
D104: 2025 | E104: ='CC 2025'!$E$78 -> 0 | F104: ='CC 2025'!$K$78 -> 0
D105: 2025 | E105: ='CC 2025'!$E$79 -> 0 | F105: ='CC 2025'!$K$79 -> 0
D106: 2025 | E106: ='CC 2025'!$E$80 -> 0 | F106: ='CC 2025'!$K$80 -> 0
D107: 2026 | E107: ='CC 2026'!$E$73 -> 0 | F107: ='CC 2026'!$K$73 -> 0
D108: 2026 | E108: ='CC 2026'!$E$74 -> 0 | F108: ='CC 2026'!$K$74 -> 0
D109: 2026 | E109: ='CC 2026'!$E$75 -> 0 | F109: ='CC 2026'!$K$75 -> 0
D110: 2026 | E110: ='CC 2026'!$E$76 -> 0 | F110: ='CC 2026'!$K$76 -> 0
D111: 2026 | E111: ='CC 2026'!$E$77 -> 0 | F111: ='CC 2026'!$K$77 -> 0
D112: 2026 | E112: ='CC 2026'!$E$78 -> 0 | F112: ='CC 2026'!$K$78 -> 0
D113: 2026 | E113: ='CC 2026'!$E$79 -> 0 | F113: ='CC 2026'!$K$79 -> 0
D114: 2026 | E114: ='CC 2026'!$E$80 -> 0 | F114: ='CC 2026'!$K$80 -> 0
